pmem/__init__.py
pmem/async_pmem.py
pmem/pickle_memory.py
pmem/sqlite_memory2.py
pmem/sync_pmem.py
pppmem-0.1.4.dist-info/METADATA
pppmem-0.1.4.dist-info/WHEEL
pppmem-0.1.4.dist-info/top_level.txt
pppmem-0.1.4.dist-info/RECORD
